socialbrute/__init__.py
socialbrute/browser.py
socialbrute/cli.py
socialbrute/helpers.py
socialbrute/socialbrute.py
socialbrute/modules/__init__.py
socialbrute/modules/aol.py
socialbrute/modules/facebook.py
socialbrute/modules/github.py
socialbrute/modules/gitlab.py
socialbrute/modules/gmail.py
socialbrute/modules/hotmail.py
socialbrute/modules/instagram.py
socialbrute/modules/linkedin.py
socialbrute/modules/netflix.py
socialbrute/modules/spotify.py
socialbrute/modules/twitter.py
socialbrute/modules/vk.py
socialbrute/modules/yahoo.py
socialbrute-1.1.0.dist-info/LICENSE
socialbrute-1.1.0.dist-info/METADATA
socialbrute-1.1.0.dist-info/WHEEL
socialbrute-1.1.0.dist-info/entry_points.txt
socialbrute-1.1.0.dist-info/top_level.txt
socialbrute-1.1.0.dist-info/RECORD
